odoo/addons/connector_jira_tempo_base/README.rst
odoo/addons/connector_jira_tempo_base/__init__.py
odoo/addons/connector_jira_tempo_base/__manifest__.py
odoo/addons/connector_jira_tempo_base/i18n/connector_jira_tempo_base.pot
odoo/addons/connector_jira_tempo_base/models/__init__.py
odoo/addons/connector_jira_tempo_base/models/account_analytic_line/__init__.py
odoo/addons/connector_jira_tempo_base/models/account_analytic_line/common.py
odoo/addons/connector_jira_tempo_base/readme/CONTRIBUTORS.rst
odoo/addons/connector_jira_tempo_base/readme/DESCRIPTION.rst
odoo/addons/connector_jira_tempo_base/static/description/icon.png
odoo/addons/connector_jira_tempo_base/static/description/index.html
odoo/addons/connector_jira_tempo_base/tests/__init__.py
odoo/addons/connector_jira_tempo_base/views/jira_backend.xml
odoo13_addon_connector_jira_tempo_base-13.0.1.0.1.dist-info/METADATA
odoo13_addon_connector_jira_tempo_base-13.0.1.0.1.dist-info/WHEEL
odoo13_addon_connector_jira_tempo_base-13.0.1.0.1.dist-info/top_level.txt
odoo13_addon_connector_jira_tempo_base-13.0.1.0.1.dist-info/RECORD
