Metadata-Version: 2.1
Name: odoo13-addon-connector-jira-tempo-base
Version: 13.0.1.0.1
Summary: Base for JIRA Connector Tempo
Home-page: https://github.com/OCA/connector-jira
Author: Brainbean Apps, Camptocamp, Odoo Community Association (OCA)
Author-email: support@odoo-community.org
License: AGPL-3
Platform: UNKNOWN
Classifier: Programming Language :: Python
Classifier: Framework :: Odoo
Classifier: License :: OSI Approved :: GNU Affero General Public License v3
Requires-Python: >=3.5
Requires-Dist: odoo13-addon-connector-jira
Requires-Dist: odoo (<13.1dev,>=13.0a)
